CHANGES.txt
README.txt
bootstrap.py
buildout.cfg
setup.py
version.txt
src/__init__.py
src/zopyx/__init__.py
src/zopyx.convert.egg-info/PKG-INFO
src/zopyx.convert.egg-info/SOURCES.txt
src/zopyx.convert.egg-info/dependency_links.txt
src/zopyx.convert.egg-info/entry_points.txt
src/zopyx.convert.egg-info/namespace_packages.txt
src/zopyx.convert.egg-info/not-zip-safe
src/zopyx.convert.egg-info/requires.txt
src/zopyx.convert.egg-info/top_level.txt
src/zopyx/convert/LICENSE.txt
src/zopyx/convert/__init__.py
src/zopyx/convert/cli.py
src/zopyx/convert/config.py
src/zopyx/convert/convert.py
src/zopyx/convert/fo2fop.py
src/zopyx/convert/fo2pdf.py
src/zopyx/convert/fo2xfc.py
src/zopyx/convert/header.txt
src/zopyx/convert/html2fo.py
src/zopyx/convert/interfaces.py
src/zopyx/convert/logger.py
src/zopyx/convert/util.py
src/zopyx/convert/lib/csstoxslfo/css2xslfo.jar
src/zopyx/convert/tests/__init__.py
src/zopyx/convert/tests/testConverters.py
src/zopyx/convert/tests/data/__init__.py
src/zopyx/convert/tests/data/test1.html
src/zopyx/convert/tests/data/test2.html
src/zopyx/convert/tests/data/test3.html