Metadata-Version: 1.0
Name: zopyx.convert
Version: 1.1.8
Summary: A Python interface to XSL-FO libraries (Conversion HTML to PDF, RTF, DOCX, WML and ODT)
Home-page: http://cheeseshop.python.org/pypi/zopyx.convert
Author: Andreas Jung
Author-email: info@zopyx.com
License: ZPL (see LICENSE.txt)
Platform: UNKNOWN
Classifier: Programming Language :: Python
